{
    "success": true,
    "wmslayers": [
        {
            "topic": "cadastre_fonds_et_overlay",
            "groupname": "Cadastre",
            "layername": "CS_BATI_POL",
            "toclayertitle": "Bâtiments",
            "visini": true,
            "wms_sort": 8,
            "toc_sort": 8
        },
        {
            "topic": "cadastre_fonds_et_overlay",
            "groupname": "Cadastre",
            "layername": "BF_PARC_POL",
            "toclayertitle": "Parcelles",
            "visini": true,
            "wms_sort": 7,
            "toc_sort": 7
        },
        {
            "topic": "cadastre_fonds_et_overlay",
            "groupname": "Cadastre",
            "layername": "PF_PFA",
            "toclayertitle": "Points fixes altimétriques",
            "visini": true,
            "wms_sort": 6,
            "toc_sort": 6
        },
        {
            "topic": "cadastre_fonds_et_overlay",
            "groupname": "Cadastre",
            "layername": "PF_PFP",
            "toclayertitle": "Points fixes planimétriques",
            "visini": true,
            "wms_sort": 5,
            "toc_sort": 5
        },
        {
            "topic": "cadastre_fonds_et_overlay",
            "groupname": "Fonds",
            "layername": "LIM_COM",
            "toclayertitle": "Limites communales",
            "visini": true,
            "wms_sort": 4,
            "toc_sort": 4
        },
        {
            "topic": "cadastre_fonds_et_overlay",
            "groupname": "Fonds",
            "layername": "Orthophotos Lidar 2012",
            "toclayertitle": "Orthophotos 2012",
            "visini": false,
            "wms_sort": 3,
            "toc_sort": 3
        },
        {
            "topic": "cadastre_fonds_et_overlay",
            "groupname": "Fonds",
            "layername": "Fond cadastral",
            "toclayertitle": "Plan cadastral",
            "visini": true,
            "wms_sort": 2,
            "toc_sort": 2
        },
        {
            "topic": "cadastre_fonds_et_overlay",
            "groupname": "Fonds",
            "layername": "Plan ville",
            "toclayertitle": "Plan Ville",
            "visini": false,
            "wms_sort": 1,
            "toc_sort": 1
        },
        {
            "topic": "cadastre_fonds_et_overlay",
            "groupname": "Fonds",
            "layername": "Carte nationale",
            "toclayertitle": "Carte nationale",
            "visini": false,
            "wms_sort": 0,
            "toc_sort": 0
        }
    ]
}
        
